<?xml version="1.0" encoding="UTF-8"?>
<objects serializationModel="Studio.02.02.00">
	<object class="AudioFile" id="{b3484b6e-3dd0-4d5a-a0a6-a92a4c79f0a4}">
		<property name="assetPath">
			<value>VoiceLines/ProfessorMay_Spooktober/338.wav</value>
		</property>
		<property name="frequencyInKHz">
			<value>44.0999985</value>
		</property>
		<property name="channelCount">
			<value>2</value>
		</property>
		<property name="length">
			<value>3.2167573696145126</value>
		</property>
		<relationship name="masterAssetFolder">
			<destination>{69d00c0e-406c-45fa-b799-c4067baf9c2e}</destination>
		</relationship>
	</object>
</objects>
